opengeode_stochastic/__init__.py
opengeode_stochastic/__init__.pyi
opengeode_stochastic/py.typed
opengeode_stochastic/stochastic.py
opengeode_stochastic/stochastic.pyi
opengeode_stochastic/lib64/__init__.pyi
opengeode_stochastic/lib64/libOpenGeode-Stochastic_stochastic.so
opengeode_stochastic/lib64/opengeode_stochastic_py_stochastic.cpython-310-x86_64-linux-gnu.so
opengeode_stochastic/lib64/opengeode_stochastic_py_stochastic.pyi
opengeode_stochastic-1.19.1.dist-info/METADATA
opengeode_stochastic-1.19.1.dist-info/WHEEL
opengeode_stochastic-1.19.1.dist-info/top_level.txt
opengeode_stochastic-1.19.1.dist-info/RECORD
