Metadata-Version: 2.4
Name: OpenGeode-Stochastic
Version: 1.19.1
Summary: A module of the OpenGeode framework for stochastic modeling, simulation and bayesian inference
Author-email: Geode-solutions <contact@geode-solutions.com>
License: MIT
Requires-Python: <3.13,>=3.9
Requires-Dist: opengeode-core==15.*,>=15.30.11
